{
  "kind": "exposure_paths",
  "asset_id": "NVDA",
  "direction": "long",
  "horizon": "any",
  "status": "ok",
  "live_path_count": 5,
  "planned_path_count": 1,
  "paths": [
    {
      "path_id": "long_stock",
      "instrument_rail": "spot_equity",
      "label": "Own shares",
      "direction": "long",
      "headline": "Full upside and downside — no expiry",
      "capital_shape": "100% of position at risk on spot move",
      "leverage": "none",
      "time_bound": "none",
      "liquidity": "high",
      "trust_badge": "Live",
      "pros": [
        "Simplest path — no theta decay",
        "Full participation in spot moves"
      ],
      "cons": [
        "Full downside if price falls",
        "More capital per unit of exposure than options"
      ],
      "recommendation_status": "path_not_recommendation",
      "sort_group": "spot_equity",
      "fit_lenses": [
        "simplest",
        "liquid"
      ],
      "cost_hint_usd": 18000.0
    },
    {
      "path_id": "bull_call_spread_leaps",
      "instrument_rail": "listed_options",
      "label": "Bull call spread (LEAPS)",
      "direction": "long",
      "headline": "Defined-risk bullish options structure",
      "capital_shape": "Net debit at risk; capped upside above short strike",
      "leverage": "defined",
      "time_bound": "dated",
      "liquidity": "medium",
      "trust_badge": "Live",
      "pros": [
        "Lower cost than naked long call",
        "Max loss known at entry"
      ],
      "cons": [
        "Upside capped at short call strike",
        "Still subject to time decay"
      ],
      "recommendation_status": "path_not_recommendation",
      "sort_group": "listed_options_defined_risk",
      "fit_lenses": [
        "defined_risk",
        "patient",
        "liquid",
        "capital_light"
      ],
      "cost_hint_usd": 650.0,
      "legs": [
        {
          "side": "BUY",
          "instrument": "NVDA Call",
          "strike": "$180",
          "tenor": "2027-04-25"
        },
        {
          "side": "SELL",
          "instrument": "NVDA Call",
          "strike": "$198",
          "tenor": "2027-04-25"
        }
      ],
      "deep_link": "/strategy-lab?asset=NVDA"
    },
    {
      "path_id": "long_leaps_call",
      "instrument_rail": "listed_options",
      "label": "Long LEAPS call",
      "direction": "long",
      "headline": "Leveraged upside with premium at risk",
      "capital_shape": "Premium at risk; leverage vs spot",
      "leverage": "defined",
      "time_bound": "dated",
      "liquidity": "medium",
      "trust_badge": "Live",
      "pros": [
        "Less capital than owning shares for similar upside bias",
        "Defined max loss (premium paid)"
      ],
      "cons": [
        "Time decay; must be right before expiry",
        "LEAPS chain may be thin — check trust badge"
      ],
      "recommendation_status": "path_not_recommendation",
      "sort_group": "listed_options_leaps",
      "fit_lenses": [
        "defined_risk",
        "patient",
        "liquid"
      ],
      "cost_hint_usd": 1250.0,
      "legs": [
        {
          "side": "BUY",
          "instrument": "NVDA Call",
          "strike": "$180",
          "tenor": "2027-04-25"
        }
      ],
      "deep_link": "/strategy-lab?asset=NVDA"
    },
    {
      "path_id": "long_near_dated_call",
      "instrument_rail": "listed_options",
      "label": "Long call (3–6 months)",
      "direction": "long",
      "headline": "Shorter-dated bullish options",
      "capital_shape": "Premium at risk",
      "leverage": "high",
      "time_bound": "dated",
      "liquidity": "medium",
      "trust_badge": "Live",
      "pros": [
        "Lower premium than LEAPS",
        "More leverage per dollar if move is near-term"
      ],
      "cons": [
        "Faster time decay",
        "Timing risk higher than LEAPS"
      ],
      "recommendation_status": "path_not_recommendation",
      "sort_group": "listed_options_aggressive",
      "fit_lenses": [
        "upside_leverage",
        "liquid"
      ],
      "cost_hint_usd": 1250.0,
      "legs": [
        {
          "side": "BUY",
          "instrument": "NVDA Call",
          "strike": "$180",
          "tenor": "2026-09-28"
        }
      ],
      "deep_link": "/strategy-lab?asset=NVDA"
    },
    {
      "path_id": "long_otm_call",
      "instrument_rail": "listed_options",
      "label": "Long OTM call",
      "direction": "long",
      "headline": "High leverage, low probability payoff",
      "capital_shape": "Small premium; likely total loss if spot stays below strike",
      "leverage": "high",
      "time_bound": "dated",
      "liquidity": "low",
      "trust_badge": "Live",
      "pros": [
        "Low cash outlay for large notional exposure if right"
      ],
      "cons": [
        "Low probability of profit vs ATM structures",
        "Sensitive to vol and time"
      ],
      "recommendation_status": "path_not_recommendation",
      "sort_group": "listed_options_aggressive",
      "fit_lenses": [
        "upside_leverage",
        "capital_light"
      ],
      "cost_hint_usd": 600.0,
      "legs": [
        {
          "side": "BUY",
          "instrument": "NVDA Call",
          "strike": "$198",
          "tenor": "2026-09-28"
        }
      ],
      "deep_link": "/strategy-lab?asset=NVDA"
    },
    {
      "path_id": "sector_etf_proxy",
      "instrument_rail": "etf_proxy",
      "label": "Sector ETF proxy",
      "direction": "long",
      "headline": "Broader semiconductor exposure — not single-name",
      "capital_shape": "ETF spot move risk",
      "leverage": "none",
      "time_bound": "none",
      "liquidity": "planned",
      "trust_badge": "Planned",
      "pros": [
        "Diversified sector exposure"
      ],
      "cons": [
        "Not pure NVDA beta — includes other holdings",
        "Not connected in v0 — Planned only"
      ],
      "recommendation_status": "path_not_recommendation",
      "sort_group": "etf_proxy"
    }
  ],
  "sections": [
    {
      "section_key": "spot_equity",
      "title": "Spot — simplest",
      "subcopy": "No expiry; full delta on the underlying",
      "path_ids": [
        "long_stock"
      ]
    },
    {
      "section_key": "listed_options_defined_risk",
      "title": "Defined-risk options",
      "subcopy": "Premium or net debit caps worst case",
      "path_ids": [
        "bull_call_spread_leaps"
      ]
    },
    {
      "section_key": "listed_options_leaps",
      "title": "Longer-dated options",
      "subcopy": "More time; usually higher premium",
      "path_ids": [
        "long_leaps_call"
      ]
    },
    {
      "section_key": "listed_options_aggressive",
      "title": "Timing-sensitive",
      "subcopy": "More leverage; faster decay",
      "path_ids": [
        "long_near_dated_call",
        "long_otm_call"
      ]
    },
    {
      "section_key": "planned_context",
      "title": "Planned — context only",
      "subcopy": "Not connected yet; shown for honesty",
      "path_ids": [
        "sector_etf_proxy"
      ]
    }
  ],
  "recommendation_status": "path_not_recommendation",
  "footer_copy": "Paths for comparison only — simulation and research support, not trade recommendations.",
  "spot_usd": 180.0,
  "proof_asset": true
}
